setup.cfg
setup.py
collective/__init__.py
collective.validator.css.egg-info/PKG-INFO
collective.validator.css.egg-info/SOURCES.txt
collective.validator.css.egg-info/dependency_links.txt
collective.validator.css.egg-info/entry_points.txt
collective.validator.css.egg-info/namespace_packages.txt
collective.validator.css.egg-info/not-zip-safe
collective.validator.css.egg-info/requires.txt
collective.validator.css.egg-info/top_level.txt
collective/validator/__init__.py
collective/validator/css/HISTORY.txt
collective/validator/css/README.txt
collective/validator/css/__init__.py
collective/validator/css/adapter.py
collective/validator/css/config.py
collective/validator/css/configure.zcml
collective/validator/css/refresh.txt
collective/validator/css/version.txt
collective/validator/css/i18n/collective.validator.css-it.po
collective/validator/css/interfaces/__init__.py
collective/validator/css/interfaces/interfaces.py
collective/validator/css/tests/__init__.py
collective/validator/css/tests/test_plone_validation.py