Metadata-Version: 1.0
Name: collective.validator.css
Version: 1.0.2beta
Summary: CSS Validator for collective.validator.base package
Home-page: https://svn.plone.org/svn/collective/collective.validator.css
Author: Andrea Cecchi
Author-email: info@redturtle.net
License: GPL
Keywords: Plone Validator XHTML CSS
Platform: UNKNOWN
Classifier: Framework :: Plone
Classifier: Framework :: Zope2
Classifier: Framework :: Zope3
Classifier: Programming Language :: Python
Classifier: Topic :: Software Development :: Libraries :: Python Modules
